pydlmodels.py
pydlmodels-0.1.4.dist-info/LICENSE
pydlmodels-0.1.4.dist-info/METADATA
pydlmodels-0.1.4.dist-info/WHEEL
pydlmodels-0.1.4.dist-info/top_level.txt
pydlmodels-0.1.4.dist-info/RECORD
