Metadata-Version: 2.1
Name: pydlmodels
Version: 0.1.4
Summary: A package for deep learning models and data preprocessing
Home-page: https://www.drateendrajha.com/projects/pydlmodels
Author: Ateendra Jha
Author-email: ateendrajha@live.com
Keywords: python,pandas,numpy,basic libraries,models,deep learning,resnet,nlp
Classifier: Programming Language :: Python :: 3
Classifier: License :: OSI Approved :: MIT License
Classifier: Operating System :: OS Independent
Requires-Python: >=3.6
License-File: LICENSE
Requires-Dist: pybaseanal
Requires-Dist: torch
Requires-Dist: termcolor
Requires-Dist: datetime
Requires-Dist: torchvision
Requires-Dist: tqdm
Requires-Dist: nltk
